<?xml version="1.0" encoding="UTF-8"?>

<library name="Explorer">
  <include file="ProcessManager/RecentProcesses.h"/>
  <import name="WorkUnitManager"/>

  <!-- Explorer Configuration -->
  <class name="RecentFileVector">
    <variable type="LocalFile" name="recentDirectory"/>
    <variable type="GenericVector[LocalFile]" name="recentFiles"/>
  </class>

  <class name="ExplorerConfiguration" base="Object">
    <variable type="RecentFileVector" name="recentProjects"/>
  </class>

  <!-- Project -->
  <class name="RecentWorkUnitConfiguration" base="Object">
    <variable type="String" name="workUnitName"/>
    <variable type="GenericVector[String]" name="arguments"/>
    <variable type="GenericVector[LocalFile]" name="workingDirectories"/>
  </class>

  <class name="RecentWorkUnitsConfiguration" base="Object">
    <variable type="ObjectVector[RecentWorkUnitConfiguration]" name="recents"/>
  </class>
  
  <class name="ExplorerProject">
    <variable type="LocalFile" name="rootDirectory"/>
    <variable type="LocalFile" name="recentDirectory"/>
    <variable type="RecentWorkUnitsConfiguration" name="recentWorkUnits"/>
    
    <variable type="Boolean" name="managerConnected"/>
    <variable type="String" name="managerHostName"/>
    <variable type="Integer" name="managerPort"/>
  </class>

  <!-- Old -->
  <class name="RecentProcesses"/>
  <class name="ProcessConsoleSettings"/>
  <class name="ProcessConsoleFilter"/>

</library>
