<?xml version="1.0" encoding="UTF-8"?>

<library name="UserInterface" directory="UserInterface">

  <import name="UserInterfaceComponent"/>
  <import name="UserInterfacePlot"/>

  <include file="lbcpp/UserInterface/Plot.h"/>
  <include file="lbcpp/UserInterface/Histogram.h"/>
  <include file="lbcpp/UserInterface/PieChart.h"/>

  <!-- Objects -->
  <class name="PlotVariable">
    <variable type="Object" name="key"/>
    <variable type="NewBoolean" name="selected"/>
    <!--<variable type="Colour" name="colour"/> -->
  </class>

  <class name="PlotAxis">
    <variable type="NewDouble" name="rangeMin"/>
    <variable type="NewDouble" name="rangeMax"/>
    <variable type="NewBoolean" name="autoRange"/>
    <variable type="NewBoolean" name="logScale"/>
    <variable type="NewString" name="unit"/>
    <variable type="NewString" name="label"/>
  </class>

  <class name="Plot">
    <variable type="PlotAxis" name="xAxis"/>
    <variable type="PlotAxis" name="yAxis"/>
    <variable type="ObjectVector[PlotVariable]" name="variables"/>
    <variable type="NewPositiveInteger" name="keyVariableIndex"/>
  </class>
  
  <class name="PieChart" base="Object">
    <variable type="ObjectVector[Pair[NewString, NewDouble]]" name="values"/>
  </class>

  <class name="Histogram" base="NameableObject">
    <variable type="NewDouble" name="stepSize"/>
    <variable type="NewDouble" name="minValue"/>
    <variable type="NewDouble" name="maxValue"/>
    <variable type="NewBoolean" name="includeOutOfBound"/>
    <variable type="DenseDoubleVector[PositiveIntegerEnumeration,NewDouble]" name="values"/>
  </class>

</library>
